pyattest/__init__.py
pyattest/__version__.py
pyattest/assertion.py
pyattest/attestation.py
pyattest/exceptions.py
pyattest/certificates/Apple_App_Attestation_Root_CA.pem
pyattest/configs/__init__.py
pyattest/configs/apple.py
pyattest/configs/config.py
pyattest/configs/google.py
pyattest/configs/google_play_integrity_api.py
pyattest/testutils/__init__.py
pyattest/testutils/factories/__init__.py
pyattest/testutils/factories/certificates.py
pyattest/testutils/factories/attestation/__init__.py
pyattest/testutils/factories/attestation/apple.py
pyattest/testutils/factories/attestation/google.py
pyattest/testutils/fixtures/root_cert.pem
pyattest/testutils/fixtures/root_key.pem
pyattest/verifiers/__init__.py
pyattest/verifiers/apple_assertion.py
pyattest/verifiers/apple_attestation.py
pyattest/verifiers/assertion.py
pyattest/verifiers/attestation.py
pyattest/verifiers/google_assertion.py
pyattest/verifiers/google_attestation.py
pyattest/verifiers/google_play_integrity_attestation.py
pyattest/verifiers/utils.py
pyattest-1.0.4.dist-info/licenses/LICENSE
pyattest-1.0.4.dist-info/METADATA
pyattest-1.0.4.dist-info/WHEEL
pyattest-1.0.4.dist-info/top_level.txt
pyattest-1.0.4.dist-info/RECORD
