Metadata-Version: 2.4
Name: pyattest
Version: 1.0.4
Home-page: https://github.com/dreipol/pyattest
Author: dreipol
Author-email: dev@dreipol.ch
License: MIT
Classifier: License :: OSI Approved :: MIT License
Classifier: Programming Language :: Python
Classifier: Programming Language :: Python :: 3
Classifier: Programming Language :: Python :: 3.6
Classifier: Programming Language :: Python :: Implementation :: CPython
Classifier: Programming Language :: Python :: Implementation :: PyPy
Requires-Python: >=3.6.0
License-File: LICENSE
Requires-Dist: cbor2
Requires-Dist: pyhanko_certvalidator
Requires-Dist: pyjwt
Requires-Dist: python-jose[cryptography]
Requires-Dist: cryptography
Dynamic: author
Dynamic: author-email
Dynamic: classifier
Dynamic: description
Dynamic: description-content-type
Dynamic: home-page
Dynamic: license
Dynamic: license-file
Dynamic: requires-dist
Dynamic: requires-python
